dict_to_dataclass/__init__.py
dict_to_dataclass/_base_class.py
dict_to_dataclass/_type_utils.py
dict_to_dataclass/exceptions.py
dict_to_dataclass/_converters/__init__.py
dict_to_dataclass/_converters/datetime_converter.py
dict_to_dataclass/_converters/enum_converter.py
dict_to_dataclass-0.0.8.dist-info/LICENCE
dict_to_dataclass-0.0.8.dist-info/METADATA
dict_to_dataclass-0.0.8.dist-info/WHEEL
dict_to_dataclass-0.0.8.dist-info/top_level.txt
dict_to_dataclass-0.0.8.dist-info/RECORD
