Metadata-Version: 2.1
Name: dict-to-dataclass
Version: 0.0.8
Summary: Utils for mapping dataclass fields to dictionary keys, making it possible to create an instance of a dataclass from a dictionary.
Home-page: https://github.com/jackd68ed/dict-to-dataclass
Author: Daniel Jack
Author-email: jackd68ed@googlemail.com
License: UNKNOWN
Platform: UNKNOWN
Classifier: Programming Language :: Python :: 3
Classifier: License :: OSI Approved :: MIT License
Classifier: Operating System :: OS Independent
Requires-Python: >=3.7
Requires-Dist: python-dateutil (==2.8.1)
